{
  "name": "fraenki-galera",
  "version": "1.0.6",
  "author": "Frank Wall",
  "summary": "Install/configure MySQL with Galera",
  "license": "BSD-2-Clause",
  "source": "https://github.com/fraenki/puppet-galera",
  "project_page": "https://github.com/fraenki/puppet-galera",
  "issues_url": "https://github.com/fraenki/puppet-galera/issues",
  "dependencies": [
    {
      "name": "puppetlabs/stdlib",
      "version_requirement": ">= 4.2.0 < 7.0.0"
    },
    {
      "name": "puppetlabs/apt",
      "version_requirement": ">= 4.0.0 < 8.0.0"
    },
    {
      "name": "puppetlabs/mysql",
      "version_requirement": ">= 6.0.0 < 11.0.0"
    },
    {
      "name": "puppetlabs/firewall",
      "version_requirement": ">= 1.0.0 < 3.0.0"
    },
    {
      "name": "puppetlabs/xinetd",
      "version_requirement": ">= 2.0.0 < 4.0.0"
    },
    {
      "name": "stahnma/epel",
      "version_requirement": ">= 1.2.2 < 3.0.0"
    }
  ],
  "operatingsystem_support": [
    {
      "operatingsystem": "Debian",
      "operatingsystemrelease": [
        "8",
        "9",
        "10"
      ]
    },
    {
      "operatingsystem": "Ubuntu",
      "operatingsystemrelease": [
        "16.04",
        "18.04"
      ]
    },
    {
      "operatingsystem": "RedHat",
      "operatingsystemrelease": [
        "6",
        "7",
        "8"
      ]
    },
    {
      "operatingsystem": "CentOS",
      "operatingsystemrelease": [
        "6",
        "7",
        "8"
      ]
    },
    {
      "operatingsystem": "FreeBSD"
    }
  ],
  "requirements": [
    {
      "name": "puppet",
      "version_requirement": ">= 5.5.8 < 7.0.0"
    }
  ],
  "description": "Install/configure MySQL with Galera/XtraDB cluster support",
  "tags": [
    "mysql",
    "percona",
    "mariadb",
    "galera",
    "database",
    "codership",
    "cluster",
    "wsrep",
    "xtradb"
  ],
  "pdk-version": "1.16.0",
  "template-url": "pdk-default#1.16.0",
  "template-ref": "tags/1.16.0-0-gaf44904"
}
